QCharted.py
QCharted-1.1.3.dist-info/LICENSE
QCharted-1.1.3.dist-info/METADATA
QCharted-1.1.3.dist-info/WHEEL
QCharted-1.1.3.dist-info/top_level.txt
QCharted-1.1.3.dist-info/RECORD
