Metadata-Version: 2.1
Name: QCharted
Version: 1.1.3
Summary: Plotting large data series using PyQtChart.
Home-page: https://github.com/arnobaer/QCharted
Author: Bernhard Arnold
Author-email: bernhard.arnold@oeaw.ac.at
License: GPLv3
License-File: LICENSE
Requires-Dist: numpy (>=1.17)
Requires-Dist: PyQt5 (>=5.12)
Requires-Dist: PyQtChart (>=5.12)
